[
	{
		"NAME":"-No Selection-",
		"COUNTY":["-No Selection-", "Davis", "Salt Lake", "Weber"],
		"CITY":["-No Selection-", "Bluffdale", "Bountiful", "Centerville", "Clearfield", "Clinton", "Copperton", "Cottonwood Heights", "Draper", "Emigration Canyon", "Farmington", "Farr West", "Fruit Heights", "Harrisville", "Herriman", "Holladay", "Hooper", "Kaysville", "Kearns Township", "Layton", "Magna Township", "Marriott-Slaterville", "Midvale", "Millcreek", "Murray", "None", "North Ogden", "North Salt Lake", "Ogden", "Plain City", "Pleasant View", "Riverdale", "Riverton", "Roy", "Salt Lake City", "Sandy", "South Jordan", "South Ogden", "South Salt Lake", "South Weber", "Sunset", "Syracuse", "Taylorsville", "Uintah", "Washington Terrace", "West Bountiful", "West Haven", "West Jordan", "West Point", "West Valley City", "White City Township", "Woods Cross"],
		"CENTER":["-No Selection-", "12600 South Mountain View Corridor", "21st and 21st", "2300 East 3300 South", "2600 South Center", "2700 South Station", "4800 South Redwood", "5400 South Redwood", "7th Street Sandy Point", "900 East Station", "9th and 9th Center", "Antelope & Main Town Center", "Ballpark", "Bingham Junction", "Bountiful 200 West", "Bountiful 500 South", "Bountiful Downtown", "Business Depot Ogden", "Centerville Downtown", "Church & Hwy 193 Town Center", "Clinton Town Center", "Copperton Community Center", "Cottonwood Heights Fort Union", "Cottonwood Village", "Courthouse Downtown", "Daybreak", "Decker Lake Center", "Downtown Clearfield", "Downtown Kaysville", "Downtown Riverton", "Downtown South Salt Lake", "Draper City Center", "Draper Kimballs Lane Station", "East Antelope Center", "East Gate Business Center", "Fairbourne Station", "Farr West 2700 North", "Fashion Place West", "Fireclay Center", "Five Points", "Fore Lakes Center", "Fort Union Canyon Center", "Foxboro", "Freeport Center", "Gardner Village", "Gateway Crossing", "Gentile & Fairfield Town Center", "Glendale Center", "Gordon & Fairfield Town Center", "Granary District", "Harrisville US 89", "Herriman Porter Rockwell Center", "Herriman Town Center", "Highberry Center", "Highlands Loop Center", "Highline", "Historic Magna Main Street", "Historic Sandy Station", "Holladay City Center", "Hunter Town Center", "Independence", "Ivy Place Center", "Jordan Bluffs", "Jordan Valley", "Kaysville Business Park", "Layton Downtown", "Layton Industrial Center", "Layton Midtown", "Legacy Crossing", "Legacy Gateway", "Lone Peak Parkway Employment Center", "Marketview Center", "Marmalade", "Marriott-Slaterville Employment District", "Meadowbrook Station", "Midvale Center Station", "Midvale Fort Union Station", "Midvale Main Street", "Millcreek City Center", "Millcreek Station", "Mountain View Village", "Murray Downtown", "Murray Industrial District", "Murray Medical Park", "Newgate Center", "None", "North Ogden Downtown", "North Ogden Southtown", "North Salt Lake / Woods Cross Industrial District", "North Salt Lake Town Center", "North Shore", "North Station", "North Temple Center", "Oakwood Village Center", "Ogden 12th Street", "Ogden Airport Industrial District", "Ogden Downtown", "Ogden Harrison Boulevard North", "Ogden Harrison Boulevard South", "Oquirrh View Center", "Orchard Drive 2200 South", "Pages Lane Center", "Plain City Gateway", "Pleasant Green", "Pleasant View 2700 North", "Pleasant View Employment Center", "Quarry Bend Center", "Renaissance Towne Center", "Research Park", "River Park", "River Trail Station", "Riverdale City Center", "Rose Park Center", "Roy Downtown", "Roy Station", "S-Line Center", "Salt Lake 15th and 15th", "Salt Lake 900 West", "Salt Lake City CBD", "Salt Lake City East Downtown", "Salt Lake City Northwest Quadrant", "Sandy Union Park", "Sandy Village Center", "SoDa Row", "Sorenson Research Park", "South Jordan Gateway", "South Jordan Towne Center", "South Ogden City Center", "South Ogden Gateway", "South Ogden US 89", "South Salt Lake State Street", "Station Park", "Sugarhouse", "Sunset SR 126", "Syracuse City Center", "Syracuse SR 193 Center", "Taylrosville West Point Center", "The Cairns", "The District", "Union Park", "University Gardens", "University of Utah", "Village Green Center", "Vista Station", "Washington Terrace US 89", "Weber State University", "Weber State University Davis", "West 12th Street", "West Bountiful Industrial District", "West Haven City Center", "West Haven Midland Drive", "West Jordan City Center", "West Ogden Center", "West Point City Center", "West Point West Davis", "West Riverdale Center", "West Valley Redwood Center", "West Warren Center", "West Weber", "Westpointe Center", "Wheeler Village"]
	},
	{
		"NAME":"Davis",
		"COUNTY":["-No Selection-", "Davis"],
		"CITY":["-No Selection-", "South Weber", "Clearfield", "Layton", "West Point", "Syracuse", "Kaysville", "North Salt Lake", "Centerville", "Roy", "Clinton", "None", "Bountiful", "Hooper", "Fruit Heights", "Farmington", "Sunset", "Woods Cross", "West Bountiful"],
		"CENTER":["-No Selection-", "Gentile & Fairfield Town Center", "East Gate Business Center", "Layton Industrial Center", "Bountiful Downtown", "Layton Downtown", "West Bountiful Industrial District", "East Antelope Center", "Foxboro", "North Station", "Sunset SR 126", "Weber State University Davis", "West Point West Davis", "Downtown Kaysville", "Downtown Clearfield", "North Salt Lake / Woods Cross Industrial District", "None", "2600 South Center", "Centerville Downtown", "West Point City Center", "Pages Lane Center", "Kaysville Business Park", "Syracuse SR 193 Center", "Freeport Center", "Legacy Gateway", "Gateway Crossing", "Courthouse Downtown", "Layton Midtown", "Bountiful 500 South", "Church & Hwy 193 Town Center", "Bountiful 200 West", "Station Park", "Gordon & Fairfield Town Center", "Syracuse City Center", "Clinton Town Center", "North Salt Lake Town Center", "Antelope & Main Town Center", "Legacy Crossing", "Renaissance Towne Center", "Orchard Drive 2200 South"]
	},
	{
		"NAME":"Salt Lake",
		"COUNTY":["-No Selection-", "Salt Lake"],
		"CITY":["-No Selection-", "Draper", "Bluffdale", "West Valley City", "Riverton", "Murray", "Copperton", "White City Township", "Cottonwood Heights", "South Jordan", "Herriman", "None", "Salt Lake City", "Holladay", "West Jordan", "South Salt Lake", "Midvale", "Millcreek", "Taylorsville", "Sandy", "Magna Township", "Emigration Canyon", "Kearns Township"],
		"CENTER":["-No Selection-", "Downtown Riverton", "University of Utah", "Research Park", "The District", "Murray Downtown", "Union Park", "Glendale Center", "7th Street Sandy Point", "Salt Lake City Northwest Quadrant", "Fairbourne Station", "None", "Salt Lake City East Downtown", "Murray Industrial District", "Jordan Bluffs", "Salt Lake 15th and 15th", "South Salt Lake State Street", "Murray Medical Park", "Draper City Center", "Taylrosville West Point Center", "West Jordan City Center", "Millcreek City Center", "North Temple Center", "Fashion Place West", "Midvale Main Street", "South Jordan Gateway", "Millcreek Station", "Historic Sandy Station", "Bingham Junction", "Sorenson Research Park", "5400 South Redwood", "Salt Lake City CBD", "4800 South Redwood", "Downtown South Salt Lake", "Meadowbrook Station", "12600 South Mountain View Corridor", "Fore Lakes Center", "Cottonwood Heights Fort Union", "West Valley Redwood Center", "2300 East 3300 South", "University Gardens", "Holladay City Center", "North Shore", "Highline", "Hunter Town Center", "Lone Peak Parkway Employment Center", "Copperton Community Center", "2700 South Station", "Fireclay Center", "Fort Union Canyon Center", "River Trail Station", "Cottonwood Village", "Decker Lake Center", "Village Green Center", "Jordan Valley", "S-Line Center", "Pleasant Green", "Granary District", "Midvale Center Station", "Marmalade", "The Cairns", "Gardner Village", "Sandy Union Park", "Quarry Bend Center", "South Jordan Towne Center", "River Park", "9th and 9th Center", "Midvale Fort Union Station", "Rose Park Center", "900 East Station", "Independence", "Herriman Porter Rockwell Center", "Draper Kimballs Lane Station", "Vista Station", "Mountain View Village", "Salt Lake 900 West", "Herriman Town Center", "Highberry Center", "Ballpark", "SoDa Row", "Ivy Place Center", "Daybreak", "Marketview Center", "Oakwood Village Center", "Historic Magna Main Street", "Sandy Village Center", "Westpointe Center", "Oquirrh View Center", "Sugarhouse", "21st and 21st", "Highlands Loop Center"]
	},
	{
		"NAME":"Weber",
		"COUNTY":["-No Selection-", "Weber"],
		"CITY":["-No Selection-", "Farr West", "North Ogden", "Uintah", "Pleasant View", "Marriott-Slaterville", "Washington Terrace", "Roy", "West Haven", "None", "Plain City", "South Ogden", "Hooper", "Harrisville", "Ogden", "Riverdale"],
		"CENTER":["-No Selection-", "Newgate Center", "Harrisville US 89", "West Riverdale Center", "Riverdale City Center", "Roy Downtown", "West Haven Midland Drive", "Pleasant View 2700 North", "Ogden Downtown", "West 12th Street", "Plain City Gateway", "Ogden Harrison Boulevard North", "None", "Five Points", "Washington Terrace US 89", "Marriott-Slaterville Employment District", "South Ogden Gateway", "Ogden Harrison Boulevard South", "Weber State University", "West Ogden Center", "Pleasant View Employment Center", "Business Depot Ogden", "West Warren Center", "Ogden 12th Street", "West Weber", "South Ogden City Center", "Ogden Airport Industrial District", "South Ogden US 89", "Wheeler Village", "North Ogden Downtown", "West Haven City Center", "Farr West 2700 North", "Roy Station", "North Ogden Southtown"]
	}
]
